declafe/__init__.py
declafe/agg_feature_gen/AggFeatures.py
declafe/agg_feature_gen/GroupBy.py
declafe/agg_feature_gen/__init__.py
declafe/agg_feature_gen/agg_fun/AggFun.py
declafe/agg_feature_gen/agg_fun/CountAgg.py
declafe/agg_feature_gen/agg_fun/DiffAtAgg.py
declafe/agg_feature_gen/agg_fun/LastAgg.py
declafe/agg_feature_gen/agg_fun/MaxAgg.py
declafe/agg_feature_gen/agg_fun/MeanAgg.py
declafe/agg_feature_gen/agg_fun/MinAgg.py
declafe/agg_feature_gen/agg_fun/NUniqueAgg.py
declafe/agg_feature_gen/agg_fun/StdAgg.py
declafe/agg_feature_gen/agg_fun/__init__.py
declafe/feature_gen/ChainMixin.py
declafe/feature_gen/ComplexFeatureMixin.py
declafe/feature_gen/ComposedFeature.py
declafe/feature_gen/ConstFeature.py
declafe/feature_gen/ConstructorMixin.py
declafe/feature_gen/FeatureGen.py
declafe/feature_gen/Features.py
declafe/feature_gen/OpsMixin.py
declafe/feature_gen/RollingApplyFeature.py
declafe/feature_gen/__init__.py
declafe/feature_gen/dsl.py
declafe/feature_gen/infer_dtype.py
declafe/feature_gen/types.py
declafe/feature_gen/binary/BiComposeFeature.py
declafe/feature_gen/binary/BinaryFeature.py
declafe/feature_gen/binary/MaxWith.py
declafe/feature_gen/binary/MinWith.py
declafe/feature_gen/binary/__init__.py
declafe/feature_gen/binary/ops/AddFeature.py
declafe/feature_gen/binary/ops/AndFeature.py
declafe/feature_gen/binary/ops/DivideFeature.py
declafe/feature_gen/binary/ops/EqFeature.py
declafe/feature_gen/binary/ops/GEFeature.py
declafe/feature_gen/binary/ops/GTFeature.py
declafe/feature_gen/binary/ops/LEFeature.py
declafe/feature_gen/binary/ops/LTFeature.py
declafe/feature_gen/binary/ops/ModFeature.py
declafe/feature_gen/binary/ops/MulFeature.py
declafe/feature_gen/binary/ops/OrFeature.py
declafe/feature_gen/binary/ops/SubFeature.py
declafe/feature_gen/binary/ops/__init__.py
declafe/feature_gen/binary/talib/AROONFeature.py
declafe/feature_gen/binary/talib/AROONOSCFeature.py
declafe/feature_gen/binary/talib/MIDPRICE.py
declafe-0.0.56.dist-info/LICENSE.md
declafe-0.0.56.dist-info/METADATA
declafe-0.0.56.dist-info/WHEEL
declafe-0.0.56.dist-info/top_level.txt
declafe-0.0.56.dist-info/RECORD
